saturnscore-1.2.1.dist-info/METADATA
saturnscore-1.2.1.dist-info/WHEEL
saturnscore-1.2.1.dist-info/entry_points.txt
saturnscore-1.2.1.dist-info/licenses/LICENSE
saturnscore/Saturn_coefficient.py
saturnscore/__init__.py
saturnscore-1.2.1.dist-info/RECORD
