Metadata-Version: 2.1
Name: saturnscore
Version: 1.2.1
Summary: Saturn coefficient to assess the results of an UMAP dimensionality reduction
Author-Email: Davide Chicco <davidechicco@davidechicco.it>
Classifier: Programming Language :: Python :: 3
Classifier: License :: OSI Approved :: MIT License
Classifier: Operating System :: OS Independent
Project-URL: Homepage, https://github.com/davidechicco/SaturnCoefficient_Python_package
Project-URL: Issues, https://github.com/davidechicco/SaturnCoefficient_Python_package/issues
Requires-Python: >=3.8
